whatanime/__init__.py
whatanime/me.py
whatanime/search.py
whatanime-0.2.dist-info/DESCRIPTION.rst
whatanime-0.2.dist-info/METADATA
whatanime-0.2.dist-info/RECORD
whatanime-0.2.dist-info/WHEEL
whatanime-0.2.dist-info/metadata.json
whatanime-0.2.dist-info/top_level.txt
