Metadata-Version: 2.0
Name: whatanime
Version: 0.2
Summary: A Python library for interacting with whatanime.ga. I have no relationship with the owner of whatanime.ga.
Home-page: https://github.com/lewbob9927/whatanime.py
Author: Lewis Trowbridge
Author-email: lewbob9927@gmail.com
License: UNKNOWN
Platform: UNKNOWN
Requires-Dist: requests
